healthyselfjournal/__init__.py
healthyselfjournal/__main__.py
healthyselfjournal/audio.py
healthyselfjournal/cli.py
healthyselfjournal/cli_diagnose.py
healthyselfjournal/cli_fix.py
healthyselfjournal/cli_init.py
healthyselfjournal/cli_init_app.py
healthyselfjournal/cli_insights.py
healthyselfjournal/cli_journal_cli.py
healthyselfjournal/cli_journal_desktop.py
healthyselfjournal/cli_journal_web.py
healthyselfjournal/cli_reconcile.py
healthyselfjournal/cli_session.py
healthyselfjournal/cli_summarise.py
healthyselfjournal/config.py
healthyselfjournal/errors.py
healthyselfjournal/events.py
healthyselfjournal/history.py
healthyselfjournal/insights.py
healthyselfjournal/llm.py
healthyselfjournal/llm_local.py
healthyselfjournal/mic_check.py
healthyselfjournal/model_manager.py
healthyselfjournal/session.py
healthyselfjournal/storage.py
healthyselfjournal/transcription.py
healthyselfjournal/tts.py
healthyselfjournal/desktop/__init__.py
healthyselfjournal/desktop/__main__.py
healthyselfjournal/desktop/app.py
healthyselfjournal/desktop/settings.py
healthyselfjournal/static/js/settings.js
healthyselfjournal/static/js/setup.js
healthyselfjournal/static/ts/app.ts
healthyselfjournal/utils/audio_utils.py
healthyselfjournal/utils/keys.py
healthyselfjournal/utils/pending.py
healthyselfjournal/utils/session_layout.py
healthyselfjournal/utils/session_utils.py
healthyselfjournal/utils/time_utils.py
healthyselfjournal/web/__init__.py
healthyselfjournal/web/app.py
healthyselfjournal/workers/__init__.py
healthyselfjournal/workers/transcription_worker.py
healthyselfjournal/prompts/insights.prompt.md.jinja
healthyselfjournal/prompts/question.prompt.md.jinja
healthyselfjournal/prompts/summary.prompt.md.jinja
healthyselfjournal/static/css/app.css
healthyselfjournal/static/js/app.js
healthyselfjournal/web/templates/session_shell.html.jinja
healthyselfjournal/web/templates/settings.html.jinja
healthyselfjournal/web/templates/setup.html.jinja
healthyselfjournal-0.2.9.dist-info/METADATA
healthyselfjournal-0.2.9.dist-info/WHEEL
healthyselfjournal-0.2.9.dist-info/entry_points.txt
healthyselfjournal-0.2.9.dist-info/licenses/LICENSE
healthyselfjournal-0.2.9.dist-info/RECORD
