Metadata-Version: 2.4
Name: healthyselfjournal
Version: 0.2.9
Summary: Voice journaling CLI with Whisper transcription and Claude follow-ups
License-File: LICENSE
Requires-Python: >=3.10
Requires-Dist: anthropic>=0.34.0
Requires-Dist: fastcore<2.0,>=1.6.7
Requires-Dist: gjdutils>=0.6.1
Requires-Dist: httpx>=0.27.2
Requires-Dist: jinja2>=3.1.2
Requires-Dist: numpy>=1.26
Requires-Dist: openai>=1.44.0
Requires-Dist: platformdirs>=4.3.0
Requires-Dist: python-dotenv>=1.0.1
Requires-Dist: python-fasthtml<0.13,>=0.12
Requires-Dist: pywebview>=5.1
Requires-Dist: pyyaml>=6.0.1
Requires-Dist: questionary>=2.0.1
Requires-Dist: readchar>=4.0.6
Requires-Dist: rich>=13.7.0
Requires-Dist: sounddevice>=0.4.6
Requires-Dist: soundfile>=0.12.1
Requires-Dist: tomli>=2.0; python_version < '3.11'
Requires-Dist: tqdm>=4.66.0
Requires-Dist: typer>=0.9.0
Provides-Extra: local-faster
Requires-Dist: faster-whisper>=1.0.1; extra == 'local-faster'
Provides-Extra: local-mlx
Requires-Dist: mlx-whisper; extra == 'local-mlx'
Provides-Extra: local-whispercpp
Requires-Dist: whispercpp; extra == 'local-whispercpp'
